pygedai/GEDAI.py
pygedai/GEDAI_stream.py
pygedai/__init__.py
pygedai/profiling.py
pygedai/ref_cov.py
pygedai/auxiliaries/GEDAI_nonRankDeficientAveRef.py
pygedai/auxiliaries/GEDAI_per_band.py
pygedai/auxiliaries/SENSAI.py
pygedai/auxiliaries/SENSAI_basic.py
pygedai/auxiliaries/SENSAI_fminbnd.py
pygedai/auxiliaries/__init__.py
pygedai/auxiliaries/clean_EEG.py
pygedai/auxiliaries/cov.py
pygedai/auxiliaries/create_cosine_weights.py
pygedai/auxiliaries/modwt.py
pygedai/auxiliaries/subspace_angles.py
pygedai/data/fsavLEADFIELD_4_GEDAI.mat
pygedai-1.0.3.dist-info/licenses/LICENSE
pygedai-1.0.3.dist-info/METADATA
pygedai-1.0.3.dist-info/WHEEL
pygedai-1.0.3.dist-info/top_level.txt
pygedai-1.0.3.dist-info/RECORD
