Metadata-Version: 2.4
Name: pygedai
Version: 1.0.3
Summary: PyGEDAI: Generalized Eigenvalue De-Artifacting Instrument in Python
Home-page: https://github.com/JoelKessler/PyGEDAI
Author: Joel Kessler
License: PolyForm Noncommercial License 1.0.0
Project-URL: Source, https://github.com/JoelKessler/PyGEDAI
Project-URL: License, https://github.com/JoelKessler/PyGEDAI/blob/main/LICENSE
Project-URL: Bug Tracker, https://github.com/JoelKessler/PyGEDAI/issues
Project-URL: Documentation, https://github.com/JoelKessler/PyGEDAI#readme
Classifier: License :: Other/Proprietary License
Classifier: Intended Audience :: Science/Research
License-File: LICENSE
Requires-Dist: torch>=2.2.0
Provides-Extra: torch
Requires-Dist: torch>=2.2.0; extra == "torch"
Dynamic: author
Dynamic: classifier
Dynamic: description
Dynamic: description-content-type
Dynamic: home-page
Dynamic: license
Dynamic: license-file
Dynamic: project-url
Dynamic: provides-extra
Dynamic: requires-dist
Dynamic: summary
